jsonschema_extractor/__init__.py
jsonschema_extractor/_version.py
jsonschema_extractor/attrs_extractor.py
jsonschema_extractor/compat.py
jsonschema_extractor/exceptions.py
jsonschema_extractor/extractor_set.py
jsonschema_extractor/typing_extractor.py
jsonschema_extractor/tests/__init__.py
jsonschema_extractor/tests/conftest.py
jsonschema_extractor/tests/test_attrs.py
jsonschema_extractor/tests/test_attrs_future_annotations.py
jsonschema_extractor/tests/test_attrs_type_annotation.py
jsonschema_extractor/tests/test_attrs_validators.py
jsonschema_extractor/tests/test_full.py
jsonschema_extractor/tests/test_typing.py
jsonschema_extractor-2.0.2.dist-info/LICENSE
jsonschema_extractor-2.0.2.dist-info/METADATA
jsonschema_extractor-2.0.2.dist-info/WHEEL
jsonschema_extractor-2.0.2.dist-info/top_level.txt
jsonschema_extractor-2.0.2.dist-info/zip-safe
jsonschema_extractor-2.0.2.dist-info/RECORD
