Metadata-Version: 2.1
Name: jsonschema-extractor
Version: 2.0.2
Summary: "a framework to extract jsonschemas from a variety of models."
Home-page: https://github.com/toumorokoshi/jsonschema-extractor
Author: "Yusuke Tsutsumi",
Author-email: "yusuke@tsutsumi.io",
Classifier: Development Status :: 5 - Production/Stable
Classifier: License :: OSI Approved :: MIT License
License-File: LICENSE
Requires-Dist: enum34 ; python_version < "3.4"
Requires-Dist: typing ; python_version < "3.5"
